onebusaway/__init__.py
onebusaway/_base_client.py
onebusaway/_client.py
onebusaway/_compat.py
onebusaway/_constants.py
onebusaway/_exceptions.py
onebusaway/_files.py
onebusaway/_models.py
onebusaway/_qs.py
onebusaway/_resource.py
onebusaway/_response.py
onebusaway/_streaming.py
onebusaway/_types.py
onebusaway/_version.py
onebusaway/py.typed
onebusaway/_utils/__init__.py
onebusaway/_utils/_compat.py
onebusaway/_utils/_datetime_parse.py
onebusaway/_utils/_json.py
onebusaway/_utils/_logs.py
onebusaway/_utils/_proxy.py
onebusaway/_utils/_reflection.py
onebusaway/_utils/_resources_proxy.py
onebusaway/_utils/_streams.py
onebusaway/_utils/_sync.py
onebusaway/_utils/_transform.py
onebusaway/_utils/_typing.py
onebusaway/_utils/_utils.py
onebusaway/lib/.keep
onebusaway/resources/__init__.py
onebusaway/resources/agencies_with_coverage.py
onebusaway/resources/agency.py
onebusaway/resources/arrival_and_departure.py
onebusaway/resources/block.py
onebusaway/resources/config.py
onebusaway/resources/current_time.py
onebusaway/resources/report_problem_with_stop.py
onebusaway/resources/report_problem_with_trip.py
onebusaway/resources/route.py
onebusaway/resources/route_ids_for_agency.py
onebusaway/resources/routes_for_agency.py
onebusaway/resources/routes_for_location.py
onebusaway/resources/schedule_for_route.py
onebusaway/resources/schedule_for_stop.py
onebusaway/resources/search_for_route.py
onebusaway/resources/search_for_stop.py
onebusaway/resources/shape.py
onebusaway/resources/stop.py
onebusaway/resources/stop_ids_for_agency.py
onebusaway/resources/stops_for_agency.py
onebusaway/resources/stops_for_location.py
onebusaway/resources/stops_for_route.py
onebusaway/resources/trip.py
onebusaway/resources/trip_details.py
onebusaway/resources/trip_for_vehicle.py
onebusaway/resources/trips_for_location.py
onebusaway/resources/trips_for_route.py
onebusaway/resources/vehicles_for_agency.py
onebusaway/types/__init__.py
onebusaway/types/agencies_with_coverage_list_response.py
onebusaway-1.19.0.dist-info/METADATA
onebusaway-1.19.0.dist-info/WHEEL
onebusaway-1.19.0.dist-info/licenses/LICENSE
onebusaway-1.19.0.dist-info/RECORD
